dotedit/__init__.py
dotedit/__main__.py
dotedit/_path_completer.py
dotedit/_path_matcher.py
dotedit/_path_store.py
dotedit/completions/bash/dotedit-completion.bash
dotedit/completions/fish/dotedit.fish
dotedit/completions/zsh/_dotedit
dotedit-1.2.0.dist-info/entry_points.txt
dotedit-1.2.0.dist-info/LICENSE
dotedit-1.2.0.dist-info/WHEEL
dotedit-1.2.0.dist-info/METADATA
dotedit-1.2.0.dist-info/RECORD
