Metadata-Version: 2.1
Name: dotedit
Version: 1.2.0
Summary: Edit dotfiles easily
Home-page: https://github.com/almgru/dotedit
License: MIT
Keywords: dotfiles,config,dotedit
Author: Daniel Alm Grundström
Author-email: daniel.alm.grundstrom@protonmail.com
Requires-Python: >=3.0,<4.0
Classifier: Development Status :: 3 - Alpha
Classifier: Environment :: Console
Classifier: Intended Audience :: Developers
Classifier: Intended Audience :: End Users/Desktop
Classifier: Intended Audience :: System Administrators
Classifier: License :: OSI Approved :: MIT License
Classifier: Operating System :: POSIX :: Linux
Classifier: Programming Language :: Python :: 3
Classifier: Programming Language :: Python :: 3 :: Only
Classifier: Programming Language :: Python :: Implementation :: CPython
Classifier: Topic :: System :: Installation/Setup
Classifier: Topic :: System :: Systems Administration
Classifier: Topic :: Utilities
Project-URL: Repository, https://github.com/almgru/dotedit
